{
  "type": "pfm:furniture",
  "group": "kitchen",
  "ingredients": [
    {
      "item": "minecraft:cactus"
    },
    {
      "item": "minecraft:cactus"
    },
    {
      "item": "minecraft:cactus"
    },
    {
      "item": "minecraft:cactus"
    },
    {
      "item": "minecraft:cactus"
    },
    {
      "item": "minecraft:cactus"
    },
    {
      "item": "minecraft:cactus"
    },
    {
      "item": "minecraft:cactus"
    },
    {
      "item": "minecraft:cactus"
    }
  ],
  "result": {
    "count": 6,
    "item": "pfm:cactus_domum_ornamentum_kitchen_wall_counter"
  }
}