{
  "type": "pfm:furniture",
  "group": "chairs",
  "ingredients": [
    {
      "item": "minecraft:cactus"
    },
    {
      "item": "minecraft:cactus"
    },
    {
      "item": "minecraft:cactus"
    },
    {
      "item": "minecraft:cactus"
    },
    {
      "item": "minecraft:cactus"
    },
    {
      "item": "domum_ornamentum:cactus_extra"
    },
    {
      "item": "domum_ornamentum:cactus_extra"
    },
    {
      "item": "domum_ornamentum:cactus_extra"
    }
  ],
  "result": {
    "count": 4,
    "item": "pfm:cactus_extra_domum_ornamentum_table_basic"
  }
}